JiuLiaoZhengqianDiyiqiJinghuaDianzishu/README.md
JiuLiaoZhengqianDiyiqiJinghuaDianzishu/__init__.py
JiuLiaoZhengqianDiyiqiJinghuaDianzishu/__main__.py
JiuLiaoZhengqianDiyiqiJinghuaDianzishu/file.pdf
JiuLiaoZhengqianDiyiqiJinghuaDianzishu/index.html
jiu_liao_zhengqian_diyiqi_jinghua_dianzishu-2024.3.4.0.dist-info/METADATA
jiu_liao_zhengqian_diyiqi_jinghua_dianzishu-2024.3.4.0.dist-info/WHEEL
jiu_liao_zhengqian_diyiqi_jinghua_dianzishu-2024.3.4.0.dist-info/entry_points.txt
jiu_liao_zhengqian_diyiqi_jinghua_dianzishu-2024.3.4.0.dist-info/top_level.txt
jiu_liao_zhengqian_diyiqi_jinghua_dianzishu-2024.3.4.0.dist-info/RECORD
